t2r2/__init__.py
t2r2/config/__init__.py
t2r2/config/config.py
t2r2/dataset/__init__.py
t2r2/dataset/common.py
t2r2/dataset/control.py
t2r2/dataset/data.py
t2r2/dataset/test.py
t2r2/dataset/training.py
t2r2/flow/__init__.py
t2r2/flow/dataset.py
t2r2/flow/flow.py
t2r2/flow/trainer.py
t2r2/metrics/__init__.py
t2r2/metrics/metrics.py
t2r2/metrics/slicing_scoring.py
t2r2/model/__init__.py
t2r2/model/model.py
t2r2/selector/__init__.py
t2r2/selector/base.py
t2r2/selector/selector.py
t2r2/selector/data_cartography/__init__.py
t2r2/selector/data_cartography/data_cartography.py
t2r2/selector/dummy/__init__.py
t2r2/selector/dummy/dummy.py
t2r2/selector/slicing/__init__.py
t2r2/selector/slicing/default_slicing_functions.py
t2r2/selector/slicing/slicing.py
t2r2/selector/undersampling/__init__.py
t2r2/selector/undersampling/undersampling.py
t2r2/utils/__init__.py
t2r2/utils/callbacks.py
t2r2/utils/utils.py
t2r2/utils/curriculum_learning/__init__.py
t2r2/utils/curriculum_learning/curriculum_learning.py
t2r2/utils/data_cartography/__init__.py
t2r2/utils/data_cartography/data_cartography.py
t2r2/utils/mlflow/__init__.py
t2r2/utils/mlflow/mlflow.py
t2r2/utils/repo/__init__.py
t2r2/utils/repo/repo.py
t2r2-0.0.1.dist-info/LICENSE
t2r2-0.0.1.dist-info/METADATA
t2r2-0.0.1.dist-info/WHEEL
t2r2-0.0.1.dist-info/top_level.txt
t2r2-0.0.1.dist-info/RECORD
