Metadata-Version: 2.1
Name: t2r2
Version: 0.0.1
Summary: T2R2: train, test, record, repeat: incremental environment for AI model training
Author-email: Radosław Winiecki <radoslaw.winiecki@student.put.poznan.pl>, Nina Żukowska <nina.zukowska@student.put.poznan.pl>, Oskar Szudzik <oskar.szudzik@student.put.poznan.pl>, Antoni Solarski <antoni.solarski@student.put.poznan.pl>
Project-URL: Homepage, https://github.com/radswn/t2r2
Classifier: Programming Language :: Python :: 3
Classifier: License :: OSI Approved :: MIT License
Classifier: Operating System :: OS Independent
Requires-Python: >=3.9
License-File: LICENSE
Requires-Dist: pandas ==1.5.2
Requires-Dist: PyYAML ==6.0
Requires-Dist: scikit-learn ==1.2.2
Requires-Dist: torch ==2.1.0
Requires-Dist: transformers ==4.20.1
Requires-Dist: imblearn ==0.0
Requires-Dist: snorkel ==0.9.9
Requires-Dist: textblob ==0.17.1
Requires-Dist: mlflow ==2.5.0
Requires-Dist: dvc ==3.15.3
Requires-Dist: seaborn ==0.13.0
